ai_chat/__init__.py
ai_chat/chat.py
ai_chat/defaults.py
ai_chat/openai.py
ai_chat/store/__init__.py
ai_chat/store/base.py
ai_chat/store/sqlite.py
ai_chat/store/supabase.py
ai_chat/types.py
ai_chat/util.py
ai_chat_chain-0.2.4.dist-info/METADATA
ai_chat_chain-0.2.4.dist-info/WHEEL
ai_chat_chain-0.2.4.dist-info/RECORD
