Metadata-Version: 2.1
Name: ai-chat-chain
Version: 0.2.4
Summary: maintain chat conversation state
License: MIT
Author: erik aronesty
Author-email: erik@q32.com
Requires-Python: >=3.9,<4.0
Classifier: License :: OSI Approved :: MIT License
Classifier: Programming Language :: Python :: 3
Classifier: Programming Language :: Python :: 3.9
Classifier: Programming Language :: Python :: 3.10
Classifier: Programming Language :: Python :: 3.11
Provides-Extra: all
Provides-Extra: openai
Provides-Extra: supabase
Requires-Dist: ai-functions (>=0.4.0,<0.5.0)
Requires-Dist: openai (>=0.27.8,<0.28.0) ; extra == "openai" or extra == "all"
Requires-Dist: supabase (>=1.0.3,<2.0.0) ; extra == "supabase" or extra == "all"
